{
  "spider": "",
  "sites": [
    {
      "key": "рҹҗӮзәўзүӣв”ғйҮҮйӣҶ",
      "name": "[1718KB/s|3106ms|зЁі] рҹҗӮзәўзүӣв”ғйҮҮйӣҶ",
      "type": 1,
      "api": "https://www.hongniuzy2.com/api.php/provide/vod/",
      "searchable": 1,
      "quickSearch": 1,
      "filterable": 0
    },
    {
      "key": "рҹҘЈзҲұеқӨв”ғеҪұи§Ҷ",
      "name": "[1713KB/s|924ms|зЁі] рҹҘЈзҲұеқӨв”ғеҪұи§Ҷ",
      "type": 1,
      "api": "https://ikunzyapi.com/api.php/provide/vod/from/ikm3u8/at/json",
      "searchable": 1,
      "quickSearch": 1,
      "filterable": 0
    },
    {
      "key": "рҹ”ҘпёҸзҒ«зӢҗв”ғз§’ж’ӯ",
      "name": "[1291KB/s|517ms|зЁі] рҹ”ҘпёҸзҒ«зӢҗв”ғз§’ж’ӯ",
      "type": 1,
      "api": "https://hhzyapi.com/api.php/provide/vod/?ac=list",
      "searchable": 1,
      "quickSearch": 1,
      "filterable": 0
    },
    {
      "key": "рҹ”°йҮ‘й№°в”ғеҪұи§Ҷ",
      "name": "[1195KB/s|623ms|зЁі] рҹ”°йҮ‘й№°в”ғеҪұи§Ҷ",
      "type": 1,
      "api": "https://jyzyapi.com/provide/vod/",
      "searchable": 1,
      "quickSearch": 1,
      "filterable": 0
    },
    {
      "key": "рҹ”ҘеҰӮж„Ҹв”ғйҮҮйӣҶ",
      "name": "[908KB/s|1686ms|зЁі] рҹ”ҘеҰӮж„Ҹв”ғйҮҮйӣҶ",
      "type": 1,
      "api": "https://cj.rycjapi.com/api.php/provide/vod/",
      "searchable": 1,
      "quickSearch": 1,
      "filterable": 0
    },
    {
      "key": "рҹҺҖжһҒйҖҹв”ғйҮҮйӣҶ",
      "name": "[655KB/s|620ms|зЁі] рҹҺҖжһҒйҖҹв”ғйҮҮйӣҶ",
      "type": 1,
      "api": "https://jszyapi.com/api.php/provide/vod/",
      "searchable": 1,
      "quickSearch": 1,
      "filterable": 0
    },
    {
      "key": "рҹҚҺй«ҳжё…в”ғ2K",
      "name": "[593KB/s|2047ms|зЁі] рҹҚҺй«ҳжё…в”ғ2K",
      "type": 1,
      "api": "https://api.1080zyku.com/inc/apijson.php",
      "searchable": 1,
      "quickSearch": 1,
      "filterable": 0
    },
    {
      "key": "рҹҶ•йқһеҮЎв”ғиө„жәҗ",
      "name": "[591KB/s|1300ms|зЁі] рҹҶ•йқһеҮЎв”ғиө„жәҗ",
      "type": 1,
      "api": "http://cj.ffzyapi.com/api.php/provide/vod/",
      "searchable": 1,
      "quickSearch": 1,
      "filterable": 0
    },
    {
      "key": "рҹҚӯйқһеҮЎв”ғйҮҮйӣҶ",
      "name": "[570KB/s|1761ms|зЁі] рҹҚӯйқһеҮЎв”ғйҮҮйӣҶ",
      "type": 0,
      "api": "http://cj.ffzyapi.com/api.php/provide/vod/at/xml/",
      "searchable": 1,
      "quickSearch": 1,
      "filterable": 0
    },
    {
      "key": "рҹҢҲзҗҘзҸҖв”ғеҪұи§Ҷ",
      "name": "[539KB/s|564ms|зЁі] рҹҢҲзҗҘзҸҖв”ғеҪұи§Ҷ",
      "type": 1,
      "api": "https://www.huyaapi.com/api.php/provide/vod/from/hym3u8",
      "searchable": 1,
      "quickSearch": 1,
      "filterable": 0
    }
  ],
  "lives": [],
  "parses": []
}